qualysclient/__init__.py
qualysclient/_defaults.py
qualysclient/_util.py
qualysclient/version.py
qualysclient/_endpoints/__init__.py
qualysclient/_endpoints/_ep_assets.py
qualysclient/_endpoints/_ep_compliance.py
qualysclient/_endpoints/_ep_reports.py
qualysclient/_endpoints/_ep_session.py
qualysclient/exceptions/__init__.py
qualysclient/models/__init__.py
qualysclient/models/api.py
tests/__init__.py
tests/test_qualysclient.py
tests/test_util.py
qualysclient-0.0.4.8.3.dist-info/LICENSE
qualysclient-0.0.4.8.3.dist-info/METADATA
qualysclient-0.0.4.8.3.dist-info/WHEEL
qualysclient-0.0.4.8.3.dist-info/top_level.txt
qualysclient-0.0.4.8.3.dist-info/RECORD
