Metadata-Version: 2.1
Name: qualysclient
Version: 0.0.4.8.3
Summary: Python SDK for interacting with the Qualys API
Home-page: https://github.com/woodtechie1428/qualysclient
Author: Wood Techie
Author-email: woodtechie1428@gmail.com
Project-URL: Bug Tracker, https://github.com/woodtechie1428/qualysclient/issues
Project-URL: Documentation, https://qualysclient.readthedocs.io/en/latest/
Classifier: Programming Language :: Python :: 3
Classifier: License :: OSI Approved :: GNU General Public License v3 (GPLv3)
Classifier: Operating System :: OS Independent
Requires-Python: >=3.6
License-File: LICENSE
Requires-Dist: requests
Requires-Dist: lxml
